regression_model/VERSION
regression_model/__init__.py
regression_model/pipeline.py
regression_model/predict.py
regression_model/preprocessors.py
regression_model/train_pipeline.py
regression_model/config/config.py
regression_model/datasets/test.csv
regression_model/datasets/train.csv
regression_model/processing/data_management.py
regression_model/trained_models/regression_model.pkl
regression_model-0.2.0.dist-info/LICENCE.txt
regression_model-0.2.0.dist-info/METADATA
regression_model-0.2.0.dist-info/WHEEL
regression_model-0.2.0.dist-info/top_level.txt
regression_model-0.2.0.dist-info/RECORD
