Metadata-Version: 2.1
Name: regression-model
Version: 0.2.0
Summary: Train and deploy regression model.
Home-page: https://github.com/The-Jyotiram-Koratkar/MyRegJK_V1.0
Author: jyotiram koratkar
Author-email: jyotiramsakshi10@gmail.com
License: MIT
Download-URL: https://github.com/The-Jyotiram-Koratkar/MyRegJK_V1.0/archive/V1.0.tar.gz
Platform: UNKNOWN
Classifier: License :: OSI Approved :: MIT License
Classifier: Programming Language :: Python
Classifier: Programming Language :: Python :: 3
Classifier: Programming Language :: Python :: 3.6
Classifier: Programming Language :: Python :: Implementation :: CPython
Classifier: Programming Language :: Python :: Implementation :: PyPy
Requires-Python: >=3.6.0
Requires-Dist: numpy (<5.0.0,==1.16.5scikit-learn==0.20.2pandas==0.23.4setuptools==41.0.0wheel==0.32.3pytest>=4.6.6)
